{"en_document_basic_button.md":"4cb67677","zh_index.md":"0b85898f","en_guide_intro.md":"e01fceb6","en_guide_install.md":"a855e345","zh_guide_install.md":"0af1879f","en_guide_start.md":"4bfe4086","index.md":"cecabad8","en_index.md":"49d8589d","zh_guide_start.md":"a9bd5ddc","zh_guide_intro.md":"d233be18","en_document_basic_icon.md":"5b14530f","en_document_form_input.md":"41dc9e21","en_document_data-display_list_list.md":"abe0abc6","zh_document_basic_icon.md":"59fcfc66","en_document_feedback_message.md":"4c5dd28e","zh_document_form_input.md":"f6a15cb2","zh_document_feedback_message.md":"f4aacaf3","en_document_form_datepicker.md":"cdfe4d3f","zh_document_data-display_list_list.md":"f2f233de","zh_document_basic_button.md":"02682685","zh_document_form_datepicker.md":"a1d19f42"}
